atopile/__init__.py
atopile/__main__.py
atopile/address.py
atopile/build_steps.py
atopile/buildutil.py
atopile/config.py
atopile/config_flags.py
atopile/dataclasses.py
atopile/errors.py
atopile/layout.py
atopile/logging.py
atopile/logging_utils.py
atopile/pytest_import_by_name.py
atopile/telemetry.py
atopile/version.py
atopile/cli/__init__.py
atopile/cli/build.py
atopile/cli/cli.py
atopile/cli/configure.py
atopile/cli/create.py
atopile/cli/dev.py
atopile/cli/inspect_.py
atopile/cli/install.py
atopile/cli/kicad_ipc.py
atopile/cli/lsp.py
atopile/cli/mcp.py
atopile/cli/package.py
atopile/cli/serve.py
atopile/cli/view.py
atopile/compiler/README.md
atopile/compiler/__init__.py
atopile/compiler/_compile.py
atopile/compiler/antlr_visitor.py
atopile/compiler/ast_types.py
atopile/compiler/ast_visitor.py
atopile/compiler/build.py
atopile/compiler/deferred_executor.py
atopile/compiler/gentypegraph.py
atopile/compiler/overrides.py
atopile/compiler/parse.py
atopile/compiler/parse_utils.py
atopile/compiler/parser/.gitignore
atopile/compiler/parser/AtoLexer.g4
atopile/compiler/parser/AtoLexer.interp
atopile/compiler/parser/AtoLexer.py
atopile/compiler/parser/AtoLexer.tokens
atopile/compiler/parser/AtoLexerBase.py
atopile/compiler/parser/AtoParser.g4
atopile/compiler/parser/AtoParser.interp
atopile/compiler/parser/AtoParser.py
atopile/compiler/parser/AtoParser.tokens
atopile/compiler/parser/AtoParserBase.py
atopile/compiler/parser/AtoParserVisitor.py
atopile/compiler/parser/README.md
atopile/compiler/parser/__init__.py
atopile/compiler/parser/build.sh
atopile/compiler/parser/tree.sh
atopile/kicad_plugin/README.md
atopile/kicad_plugin/lib.py
atopile/kicad_plugin/legacy/.gitignore
atopile/kicad_plugin/legacy/common.py
atopile/kicad_plugin/legacy/plugin.py
atopile/kicad_plugin/legacy/pullgroup.py
atopile/kicad_plugin/resource/buttons.svg
atopile/kicad_plugin/resource/download.png
atopile/lsp/__init__.py
atopile/lsp/_debug_server.py
atopile/lsp/lsp_server.py
atopile/lsp/lsp_utils.py
atopile-0.14.0.dist-info/METADATA
atopile-0.14.0.dist-info/WHEEL
atopile-0.14.0.dist-info/entry_points.txt
atopile-0.14.0.dist-info/licenses/LICENSE
atopile-0.14.0.dist-info/RECORD
