Metadata-Version: 2.4
Name: atopile
Version: 0.14.0
Summary: A toolchain bringing the best of software development to the real-world!
Project-URL: Homepage, https://github.com/atopile/atopile
Project-URL: Bug Tracker, https://github.com/atopile/atopile/issues
Author-email: Ioannis Papamanoglou <ioannis@atopile.io>, Narayan Powderly <narayan@atopile.io>
License: MIT License
License-File: LICENSE
Classifier: License :: OSI Approved :: MIT License
Classifier: Operating System :: OS Independent
Classifier: Programming Language :: Python :: 3
Requires-Python: <3.15,>=3.14
Requires-Dist: antlr4-python3-runtime==4.13.2
Requires-Dist: atopile-easyeda2kicad>=0.9.7
Requires-Dist: black>=24.4.2
Requires-Dist: case-converter>=1.2.0
Requires-Dist: cookiecutter>=2.6.0
Requires-Dist: dataclasses-json>=0.6.7
Requires-Dist: deprecated~=1.2.14
Requires-Dist: fastapi-github-oidc>=0.2.1
Requires-Dist: fastapi>=0.110.0
Requires-Dist: freetype-py>=2.4
Requires-Dist: gitpython>=3.1.41
Requires-Dist: httpx>=0.28.1
Requires-Dist: jinja2>=3.1.6
Requires-Dist: kicad-python
Requires-Dist: kicadcliwrapper>=1.1.1
Requires-Dist: matplotlib>=3.7.1
Requires-Dist: mcp[cli]>=1.10.1
Requires-Dist: more-itertools>=10.4
Requires-Dist: nanobind>=2.6.1
Requires-Dist: natsort>=8.4.0
Requires-Dist: numpy>=2.2.0
Requires-Dist: ordered-set==4.1.0
Requires-Dist: pathvalidate>=3.2.1
Requires-Dist: platformdirs>=4.3.6
Requires-Dist: posthog==6.0.3
Requires-Dist: prompt-toolkit==3.0.51
Requires-Dist: psutil>=6.0.0
Requires-Dist: pydantic-settings>=2.7.1
Requires-Dist: pygls<3.0.0,>=2.0.0
Requires-Dist: pytest<10.0.0,>=9.0.0
Requires-Dist: questionary>=2.0.1
Requires-Dist: rich>=13.7.1
Requires-Dist: ruamel-yaml>=0.18.5
Requires-Dist: ruff>=0.11.0
Requires-Dist: semver>=3.0.2
Requires-Dist: sexpdata>=1.0.2
Requires-Dist: shapely>=2.0.1
Requires-Dist: truststore>=0.10.4
Requires-Dist: typer>=0.12
Requires-Dist: typing-extensions>=4.6.3
Requires-Dist: urllib3>=2.2.1
Requires-Dist: uvicorn>=0.29.0
Requires-Dist: watchdog>=4.0.0
Requires-Dist: websockets>=12.0
Requires-Dist: zstd>=1.5.6.7
